{  "windows_host_setup": {    "title": "Windows host setup"  },  "linux_host_setup": {    "title": "Linux host setup"  },  "android_target_setup": {    "title": "Android target setup"  },  "tizen_target_setup": {    "title": "Tizen target setup"  },  "build_an_application": {    "title": "Build an application"  },  "run_on_android": {    "title": "Run on Android"  },  "run_on_tizen": {    "title": "Run on Tizen"  },  "remote_debugging": {    "title": "Remote debugging"  },  "deploy_to_android_store": {    "title": "Deploy to Android store"  }}